{"cameraMode":{"drawMode":0,"name":"Shaded","section":"Shading Mode"},"sceneLighting":true,"audioPlay":false,"sceneViewState":{"m_AlwaysRefresh":false,"showFog":true,"showSkybox":true,"showFlares":true,"showImageEffects":true,"showParticleSystems":true,"showVisualEffectGraphs":true,"m_FxEnabled":true},"in2DMode":false,"pivot":{"x":960.0,"y":540.0,"z":0.0},"rotation":{"x":-0.09466700255870819,"y":0.005073983687907457,"z":-0.00048525421880185604,"w":-0.9955052733421326},"size":523.4244384765625,"orthographic":false}